vicivalve/__init__.py
vicivalve/__version__.py
vicivalve/device_codes.py
vicivalve/vicivalve.py
vicivalve-0.0.13.dist-info/LICENSE
vicivalve-0.0.13.dist-info/METADATA
vicivalve-0.0.13.dist-info/WHEEL
vicivalve-0.0.13.dist-info/top_level.txt
vicivalve-0.0.13.dist-info/RECORD
