Metadata-Version: 2.1
Name: vicivalve
Version: 0.0.13
Summary: Python API for VICI Valco Universal Electric Actuator
Home-page: https://gitlab.com/heingroup/vicivalve
Author: Sebastian Steiner
Author-email: sebastiansteiner@chem.ubc.ca
License: MIT
Requires-Python: >=3.6.0
License-File: LICENSE
Requires-Dist: ftdi-serial
